hpman/__init__.py
hpman/__version__.py
hpman/hpm.py
hpman/hpm_db.py
hpman/hpm_zoo_monkey_patch.py
hpman/m.py
hpman/primitives.py
hpman/source_helper.py
hpman-0.13.0.dist-info/LICENSE
hpman-0.13.0.dist-info/METADATA
hpman-0.13.0.dist-info/WHEEL
hpman-0.13.0.dist-info/top_level.txt
hpman-0.13.0.dist-info/RECORD
