Metadata-Version: 2.1
Name: hpman
Version: 0.13.0
Summary: A hyperparameter manager for deep learning experiments.
Home-page: https://github.com/megvii-research/hpman
Author: Xinyu Zhou
Author-email: zxy@megvii.com
Classifier: Programming Language :: Python :: 3
Classifier: License :: OSI Approved :: MIT License
Classifier: Operating System :: OS Independent
Classifier: Intended Audience :: Developers
Classifier: Intended Audience :: Science/Research
Classifier: Topic :: Scientific/Engineering :: Artificial Intelligence
Classifier: Topic :: Software Development :: Libraries :: Python Modules
Requires-Python: >=3.5
License-File: LICENSE
Requires-Dist: attrdict
